dsdtools/__init__.py
dsdtools/audio_classes.py
dsdtools/evaluate.py
dsdtools/configs/dsd100.yaml
dsdtools-0.1.3.dist-info/DESCRIPTION.rst
dsdtools-0.1.3.dist-info/METADATA
dsdtools-0.1.3.dist-info/RECORD
dsdtools-0.1.3.dist-info/WHEEL
dsdtools-0.1.3.dist-info/metadata.json
dsdtools-0.1.3.dist-info/top_level.txt
